.DS_Store
plotastrodata/__init__.py
plotastrodata/analysis_utils.py
plotastrodata/const_utils.py
plotastrodata/coord_utils.py
plotastrodata/ext_utils.py
plotastrodata/fft_utils.py
plotastrodata/fits_utils.py
plotastrodata/fitting_utils.py
plotastrodata/los_utils.py
plotastrodata/matrix_utils.py
plotastrodata/other_utils.py
plotastrodata/plot_utils.py
plotastrodata-1.7.1.dist-info/licenses/LICENSE
plotastrodata-1.7.1.dist-info/METADATA
plotastrodata-1.7.1.dist-info/WHEEL
plotastrodata-1.7.1.dist-info/top_level.txt
plotastrodata-1.7.1.dist-info/RECORD
