Metadata-Version: 2.4
Name: plotastrodata
Version: 1.7.1
Summary: plotastrodata is a tool for astronomers to create figures from FITS files and perform fundamental data analyses with ease.
Home-page: https://github.com/yusukeaso-astron/plotastrodata
Download-URL: https://github.com/yusukeaso-astron/plotastrodata
Author: yusukeaso-astron
License: GNU General Public License Version 3
Keywords: astronomy,FITS,plot
Classifier: Programming Language :: Python :: 3
Requires-Python: >=3.12
License-File: LICENSE
Requires-Dist: astropy>=7.2
Requires-Dist: corner
Requires-Dist: dynesty
Requires-Dist: emcee
Requires-Dist: matplotlib
Requires-Dist: multiprocess
Requires-Dist: numpy>=2.0
Requires-Dist: pillow
Requires-Dist: plotly
Requires-Dist: ptemcee
Requires-Dist: scikit-image
Requires-Dist: scipy
Requires-Dist: tqdm
Dynamic: download-url
Dynamic: license-file
